[
  {
    "id": 6,
    "date": "2023-07-25T16:23:49.754Z",
    "client": "66-9099-1234",
    "branch": "3",
    "details": [
      {
        "id": 133,
        "cant": "1",
        "price": "3.04"
      },
      {
        "id": 3,
        "cant": "3",
        "price": "6.72"
      },
      {
        "id": 7,
        "cant": "1",
        "price": "3.01"
      },
      {
        "id": 11,
        "cant": "4",
        "price": "2.09"
      }
    ],
    "total": 34.57
  },
  {
    "id": 2,
    "date": "2023-07-25T16:36:47.968Z",
    "client": "3",
    "branch": "3",
    "details": [
      {
        "id": 17,
        "cant": "10",
        "price": "9.50"
      },
      {
        "id": 378,
        "cant": "2",
        "price": "4.00"
      }
    ],
    "total": 103
  },
  {
    "id": 3,
    "date": "2023-07-25T18:14:43.182Z",
    "client": "1",
    "branch": "4",
    "details": [
      {
        "id": 135,
        "cant": "1",
        "price": "5.69"
      }
    ],
    "total": 5.69
  },
  {
    "id": 4,
    "date": "2023-07-25T18:15:22.660Z",
    "client": "5",
    "branch": "8",
    "details": [
      {
        "id": 153,
        "cant": "10",
        "price": "3.62"
      },
      {
        "id": 933,
        "cant": "7",
        "price": "1.90"
      }
    ],
    "total": 49.5
  },
  {
    "id": 5,
    "date": "2023-07-25T18:15:40.564Z",
    "client": "19",
    "branch": "9",
    "details": [
      {
        "id": 8,
        "cant": "4",
        "price": "7.83"
      }
    ],
    "total": 31.32
  },
  {
    "id": 6,
    "date": "2023-07-25T18:16:28.443Z",
    "client": "29",
    "branch": "7",
    "details": [
      {
        "id": 24,
        "cant": "5",
        "price": "5.57"
      },
      {
        "id": 192,
        "cant": "8",
        "price": "1.90"
      }
    ],
    "total": 43.05
  }
]